dataaetherscan/__init__.py
dataaetherscan/das.py
dataaetherscan-1.0.0.dist-info/LICENSE
dataaetherscan-1.0.0.dist-info/METADATA
dataaetherscan-1.0.0.dist-info/WHEEL
dataaetherscan-1.0.0.dist-info/top_level.txt
dataaetherscan-1.0.0.dist-info/RECORD
