Metadata-Version: 2.1
Name: dataaetherscan
Version: 1.0.0
Summary: Python integration to DataAetherScan
Author-email: DataAetherScan <it@dataaetherscan.com>
Project-URL: Homepage, https://github.com/dataaetherscan/DataAetherScan-Python
Project-URL: Issues, https://github.com/dataaetherscan/DataAetherScan-Python/issues
Classifier: Programming Language :: Python :: 3
Classifier: License :: OSI Approved :: MIT License
Classifier: Operating System :: OS Independent
Requires-Python: >=3.8
License-File: LICENSE
